{
	"class" : {
		"instantiateFromJsonDocument:" : "AR 5/30/2019 21:04" },
	"instance" : {
		"?" : "eb 6/19/2019 09:18",
		"??" : "eb 6/19/2019 09:18",
		"asJsonDocument" : "AR 6/29/2019 14:11",
		"asJsonDocumentsWithDatabase:" : "AR 6/29/2019 17:44",
		"asJsonDocumentsWithDatabaseIntern:" : "AR 6/29/2019 17:37",
		"asSurrogate" : "pre 7/12/2018 15:28",
		"basicRespondsTo:" : "eb 5/22/2019 20:06",
		"cleanse" : "pre 4/24/2019 15:33",
		"editorContents" : "pre 7/4/2018 14:50",
		"externalTransportRepresentation" : "pre 10/4/2018 13:26",
		"has:" : "pre 5/8/2017 17:05",
		"interactiveEdit" : "pre 7/11/2018 20:10",
		"isAnyOf:" : "pre 6/30/2017 15:51",
		"isBoolean" : "pre 6/6/2019 17:27",
		"isDiaryEntry" : "pre 3/7/2017 20:52",
		"isDomainObject" : "eb 6/16/2019 11:58",
		"isEvent" : "pre 3/15/2017 17:35",
		"isExtended" : "pre 8/4/2017 10:54",
		"isPerson" : "pre 4/24/2017 10:10",
		"isPlace" : "ek 4/23/2019 14:10",
		"isSimilarTo:" : "stlu 5/16/2019 13:16",
		"isToDo" : "pre 6/20/2017 20:33",
		"objectEditorAdd:" : "pre 12/5/2018 15:48",
		"objectEditorBeforeChangeConversion" : "pre 6/29/2018 14:58",
		"objectEditorPrintString" : "pre 5/4/2018 19:51",
		"objectEditorWidgetFor:" : "pre 7/11/2018 20:10",
		"objectEditorWidgetFor:withCommandHistory:" : "JK 7/2/2019 06:56" } }
