{
	"class" : {
		"integrityRules" : "pre 6/27/2018 13:12" },
	"instance" : {
		"asBibtexString" : "pre 5/31/2018 09:30",
		"bibTexFields" : "pre 11/5/2018 11:01",
		"bibTexPublicationType" : "pre 1/17/2018 08:45",
		"bibTexReferenceKey" : "pre 1/29/2018 09:46",
		"downloadAbstractFromSemanticScholar" : "pre 1/8/2018 12:44",
		"downloadCitedWorksFromSemanticScholar" : "pre 12/8/2017 16:29",
		"downloadInfoFromOpenLibrary" : "pre 10/11/2018 19:16",
		"downloadReferencedPapersFromACM" : "pre 2/23/2018 18:19",
		"downloadReferencedPapersFromSemanticScholar" : "pre 2/23/2018 18:20",
		"downloadReferencedPapersFromWOS" : "pre 1/2/2018 16:00",
		"dtrpOriginReferencePart" : "pre 12/5/2017 11:45",
		"dtrpReferenceFormat" : "pre 12/5/2017 11:12",
		"editTags" : "pre 8/30/2017 09:56",
		"externalTransportRepresentation" : "pre 11/21/2018 13:35",
		"initialize" : "pre 10/11/2018 19:15",
		"initializeForInteractiveCreate:" : "pre 9/18/2017 16:32",
		"interactiveAddToReadingList" : "pre 4/17/2018 10:42",
		"interactiveCopyBibtex" : "pre 7/17/2018 14:15",
		"interactiveCopySwaSchemaFileName" : "pre 8/6/2018 12:18",
		"interactiveRemoveFromReadingList" : "pre 4/17/2018 10:36",
		"interactiveSetRead" : "pre 4/17/2018 10:37",
		"liveprogstudyOriginKeywords" : "pre 10/26/2017 07:31",
		"liveprogstudyOriginLocations" : "pre 10/26/2017 07:31",
		"lpsStoreFreeCiteData:" : "pre 2/23/2018 18:20",
		"parts" : "pre 10/16/2017 22:08",
		"printOn:" : "pre 7/19/2017 10:32",
		"swaBibTexReferenceKey" : "pre 5/31/2018 09:38",
		"swaSchemaFileName" : "pre 9/21/2018 08:44",
		"title" : "pre 7/7/2017 16:22",
		"title:" : "pre 10/12/2018 13:51",
		"worldIconMorph" : "pre 2/21/2018 17:27" } }
