{
	"class" : {
		 },
	"instance" : {
		"BooleanClause:with:with:" : "stlu 8/3/2019 11:03",
		"BooleanQuery:with:with:with:" : "stlu 8/3/2019 11:09",
		"BracedQuery:with:with:with:" : "stlu 7/11/2019 15:42",
		"FieldQueryAny:with:with:with:" : "stlu 8/3/2019 15:02",
		"FieldQuerySingle:with:with:with:with:" : "stlu 8/3/2019 15:02",
		"ObjectQuery:with:with:with:" : "stlu 8/5/2019 13:49",
		"PhraseQuery:with:" : "stlu 8/5/2019 13:52",
		"SelectionQuery:with:with:with:" : "stlu 7/15/2019 22:02",
		"TermQueryFuzzy:with:with:" : "stlu 7/15/2019 14:27",
		"TermQueryNotFuzzy:with:" : "stlu 7/15/2019 14:23",
		"TextQuery:with:" : "stlu 8/5/2019 13:52",
		"WordQuery:with:" : "stlu 8/5/2019 13:53",
		"compile:" : "stlu 7/15/2019 21:46",
		"defaultExpression:" : "stlu 5/20/2019 14:13",
		"field:with:with:" : "stlu 8/5/2019 14:49",
		"fuzzinessDefault:with:" : "stlu 7/15/2019 14:42",
		"fuzzinessValued:with:with:" : "stlu 7/15/2019 14:42",
		"occurrenceFilter:with:" : "stlu 8/3/2019 11:03",
		"occurrenceMust:with:" : "stlu 8/3/2019 11:03",
		"occurrenceMustNot:with:" : "stlu 8/3/2019 11:03",
		"occurrenceShould:with:" : "stlu 8/3/2019 11:03",
		"phrase:with:with:with:" : "stlu 8/3/2019 23:39",
		"phraseCharacterAny:with:" : "stlu 8/3/2019 23:39",
		"phraseCharacterBackslash:with:" : "stlu 8/3/2019 23:39",
		"phraseCharacterTick:with:" : "stlu 8/3/2019 23:40",
		"text:with:with:with:" : "stlu 8/3/2019 23:37",
		"textCharacterAny:with:" : "stlu 8/3/2019 23:34",
		"textCharacterBackslash:with:" : "stlu 8/3/2019 23:28",
		"textCharacterTick:with:" : "stlu 8/3/2019 23:27" } }
